nust0/__init__.py
nust0/test_bsai.py
nust0/seecs/__init__.py
nust0/seecs/experimental/__init__.py
nust0/seecs/experimental/bsai.py
nustify-0.1.0.dist-info/METADATA
nustify-0.1.0.dist-info/WHEEL
nustify-0.1.0.dist-info/top_level.txt
nustify-0.1.0.dist-info/RECORD
