Metadata-Version: 2.2
Name: nustify
Version: 0.1.0
Summary: A Python package for exploring BSAI at SEECS.
Home-page: https://github.com/AbdulRehmanOK/nustify
Author: Abdul Rehman
Author-email: abrehman.bsai24seecs@seecs.edu.pk
Classifier: Programming Language :: Python :: 3
Classifier: License :: OSI Approved :: MIT License
Classifier: Operating System :: OS Independent
Requires-Python: >=3.6
Dynamic: author
Dynamic: author-email
Dynamic: classifier
Dynamic: home-page
Dynamic: requires-python
Dynamic: summary
